{"collection":[{"query":"what is java core","description":"tim tat ca trang web lien quan den java core","sites":[{"title":"Top 10 bí kíp Cấu trúc dữ liệu & giải thuật | Tech Talk","url":"https:\/\/edumall.vn\/course\/tim-kiem-va-khai-thac-thong-tin-hieu-qua-tren-internet","content":"Công nghệLập trìnhLập trình ứng dụngLập trình webTools & TipsSự kiệnChuyên gia nóiTâm sự coderDevvuiForgot your password? Get helpTech TalkCông nghệ90% Public cloud chạy trên LinuxQuý 3\/2017 doanh thu từ Download ứng dụng đạt mức kỉ\u2026Ngân hàng nhà nước tuyên bố cấm sử dụng tiền ảo10 mẹo để tạo Unit Test hiệu quảNeural networks tạo ra những AI thông minh như thế nào?Lập trìnhTất cảLập trình ứng dụngLập trình web20 mẹo để làm chủ Git và GitHub \u2013 phần 2Framework Microsoft .Net 4.7.1 có gì mới?7 lí do để loại bỏ React\u2019s Functional ComponentsTại sao C # là một trong những ngôn ngữ lập\u2026Tools & TipsNhững thói quen xấu khiến code của lập trình viên bốc\u2026Những thói quen xấu khiến code của lập trình viên bốc\u2026Getting Started with Entity Framework 6 Code First using MVC 5Thử một lần code mà không dùng If xem nào?5 cách giúp lập trình viên tăng năng suất làm việcSự kiệnVWS2017 \u2013 Caching \u2013 Methology and Strategies\u201CỞ Việt Nam, cơ hội để thực sự làm về Trí\u2026[ Học bổng] Học tiếng Nhật miễn phí cùng \u201D Akira\u201D-\u2026VWS2017 \u2013 Xây dựng Decentralized web trên nền tảng BlockchainHọp báo ra mắt sự kiện Vietnam Web Summit 2017Chuyên gia nóiAmanotes \u2013 kẻ viết tiếp giấc mơ game Việt?4 sai lầm có thể khiến các lập trình viên rời\u2026Lương kỹ sư IT đi Nhật có thể lên đến 165\u2026Phỏng vấn chuyên gia Machine Learning từ AdAsia về ứng dụng\u20265 điều phiền toái nhất của CSSTâm sự coderCống hiến tới mấy nhưng cứ sau 35 tuổi là \u201Cbiến\u2026Tâm sự một coder: hãy dũng cảm thành thật với con\u2026Web Dev: Cố gắng hoàn hảo sẽ cản trở bạnThay đổi code, thay đổi thế giớiThương hiệu cá nhân Dev quan trọng hơn bạn tưởngDevvuiTrang ChủLập trìnhChia sẻ FacebookTweettweethttps:\/\/github.com\/careermonk\/DataStructuresAndAlgorithmsMadeEasyhttp:\/\/www.informit.com\/store\/data-structures-and-algorithms-in-java-9780672324536http:\/\/www3.cs.stonybrook.edu\/~algorith\/book\/programs\/https:\/\/notebookbft.files.wordpress.com\/2015\/10\/clrs-solution-collection.pdfhttp:\/\/algs4.cs.princeton.edu\/home\/đâyhttp:\/\/elementsofprogramminginterviews.com\/solutionshttps:\/\/www.cs.princeton.edu\/~rs\/Algs3.c1-4\/code.txthttps:\/\/www.cs.princeton.edu\/~rs\/Algs3.c5\/code.txthttp:\/\/www-cs-faculty.stanford.edu\/~uno\/programs.htmlhttp:\/\/www.hackersdelight.org\/hdcodetxt.zipTechmasterC#giaitrinhFacebookTwittertweetTâm sự Developer phải gánh team cho công tyHệ thống AI do chính tôi xây dựng đã khiến cha tôi thất nghiệp và những điều bạn cần biết để tránh thảm cảnh tương tựHieu LeBÀI VIẾT LIÊN QUANXEM THÊMTại sao C # là một trong những ngôn ngữ lập trình phổ biến nhất trên thế giới?Lý do khiến ngôn ngữ lập trình C không bao giờ lỗi thờiCác ngôn ngữ lập trình thông dụng nhất, theo GithubChuyên gia nóiAmanotes \u2013 kẻ viết tiếp giấc mơ game Việt?4 sai lầm có thể khiến các lập trình viên rời bỏ bạnLương kỹ sư IT đi Nhật có thể lên đến 165 triệu\/ thángTâm sự coderCâu chuyện về PINGVì sao lập trình viên nữ ngày càng vắng bóng?Khi gấu muốn làm Web DeveloperXem thêmSự kiệnVWS2017 \u2013 Caching \u2013 Methology and Strategies\u201CỞ Việt Nam, cơ hội để thực sự làm về Trí tuệ nhân tạo còn quá ít, trong khi những thứ mang hình thù...[ Học bổng] Học tiếng Nhật miễn phí cùng \u201D Akira\u201D- chắp cánh ước mơXem thêmhieuld@applancer.net - Tel: 028 6264 5022","relevance":1}]}]}